[
  {
    "id": 7,
    "hotelName": "Hotel 3",
    "hotelAddress": "Adress 3",
    "rooms": []
  },
  {
    "id": 1,
    "hotelName": "Ascot Hotel",
    "hotelAddress": "New updated address",
    "rooms": [
      {
        "roomId": 6,
        "hotelId": 1,
        "roomNumber": 6,
        "price": 4000.0
      },
      {
        "roomId": 5,
        "hotelId": 1,
        "roomNumber": 4,
        "price": 3500.0
      },
      {
        "roomId": 13,
        "hotelId": 1,
        "roomNumber": 18,
        "price": 8000.0
      },
      {
        "roomId": 3,
        "hotelId": 1,
        "roomNumber": 1,
        "price": 3000.0
      },
      {
        "roomId": 2,
        "hotelId": 1,
        "roomNumber": 5,
        "price": 4000.0
      },
      {
        "roomId": 1,
        "hotelId": 1,
        "roomNumber": 3,
        "price": 3500.0
      },
      {
        "roomId": 4,
        "hotelId": 1,
        "roomNumber": 2,
        "price": 3500.0
      }
    ]
  },
  {
    "id": 6,
    "hotelName": "Zleep Hotel",
    "hotelAddress": "Adress 1",
    "rooms": []
  }
]